odoo9_addon_stock_picking_show_return-9.0.1.0.0-py2.7-nspkg.pth
odoo_addons/stock_picking_show_return/__openerp__.py
odoo_addons/stock_picking_show_return/__init__.py
odoo_addons/stock_picking_show_return/README.rst
odoo_addons/stock_picking_show_return/models/__init__.py
odoo_addons/stock_picking_show_return/models/stock_picking.py
odoo_addons/stock_picking_show_return/i18n/it.po
odoo_addons/stock_picking_show_return/i18n/es.po
odoo_addons/stock_picking_show_return/i18n/sl.po
odoo_addons/stock_picking_show_return/i18n/de.po
odoo_addons/stock_picking_show_return/i18n/fr.po
odoo_addons/stock_picking_show_return/views/stock_picking_view.xml
odoo_addons/stock_picking_show_return/tests/test_stock_picking_show_return.py
odoo_addons/stock_picking_show_return/tests/__init__.py
odoo9_addon_stock_picking_show_return-9.0.1.0.0.dist-info/top_level.txt
odoo9_addon_stock_picking_show_return-9.0.1.0.0.dist-info/WHEEL
odoo9_addon_stock_picking_show_return-9.0.1.0.0.dist-info/RECORD
odoo9_addon_stock_picking_show_return-9.0.1.0.0.dist-info/metadata.json
odoo9_addon_stock_picking_show_return-9.0.1.0.0.dist-info/DESCRIPTION.rst
odoo9_addon_stock_picking_show_return-9.0.1.0.0.dist-info/METADATA
odoo9_addon_stock_picking_show_return-9.0.1.0.0.dist-info/namespace_packages.txt
